equalizer/__init__.py
equalizer/equalizer.py
circuitpython_equalizer-0.5.2.dist-info/LICENSE
circuitpython_equalizer-0.5.2.dist-info/METADATA
circuitpython_equalizer-0.5.2.dist-info/WHEEL
circuitpython_equalizer-0.5.2.dist-info/top_level.txt
circuitpython_equalizer-0.5.2.dist-info/RECORD
