Metadata-Version: 2.1
Name: circuitpython-equalizer
Version: 0.5.2
Summary: Equalizer Graphic Representation for CircuitPython
Home-page: https://github.com/jposada202020/CircuitPython_equalizer.git
Author: Jose David M.
Author-email: "Jose D. Montoya" <equalizer@mailmeto.mozmail.com>
License: MIT
Project-URL: Homepage, https://github.com/jposada202020/CircuitPython_equalizer.git
Keywords: hardware,micropython,circuitpython,graphic,styles,widget,displayio,color,widget,equalizer,sound
Classifier: Intended Audience :: Developers
Classifier: Topic :: Software Development :: Libraries
Classifier: Topic :: Software Development :: Embedded Systems
Classifier: Topic :: System :: Hardware
Classifier: License :: OSI Approved :: MIT License
Classifier: Programming Language :: Python :: 3
License-File: LICENSE
Requires-Dist: Adafruit-Blinka
Requires-Dist: Adafruit-Blinka-Displayio
Requires-Dist: Adafruit-CircuitPython-Displayio-Layout
Provides-Extra: optional
